buildkite_sdk/__init__.py
buildkite_sdk/environment.py
buildkite_sdk/pipeline.py
buildkite_sdk/py.typed
buildkite_sdk/schema.py
buildkite_sdk-0.5.0.dist-info/METADATA
buildkite_sdk-0.5.0.dist-info/WHEEL
buildkite_sdk-0.5.0.dist-info/RECORD
