Metadata-Version: 2.4
Name: buildkite-sdk
Version: 0.5.0
Summary: Automatically generated by Nx.
Requires-Python: <4,>=3.10
Requires-Dist: jsoncomparison
Requires-Dist: jsonschema
Requires-Dist: pydantic>=2.11.7
Requires-Dist: pyyaml
Requires-Dist: requests
